oaserver/__init__.py
oaserver/data_access.py
oaserver/eval_script.py
oaserver/json_tools.py
oaserver/oa_client.py
oaserver/oa_server.py
oaserver/oa_server_file.py
oaserver/oa_server_rest.py
oaserver/threaded_server.py
oaserver/version.py
oaserver-0.1.3.dist-info/DESCRIPTION.rst
oaserver-0.1.3.dist-info/METADATA
oaserver-0.1.3.dist-info/RECORD
oaserver-0.1.3.dist-info/WHEEL
oaserver-0.1.3.dist-info/entry_points.txt
oaserver-0.1.3.dist-info/metadata.json
oaserver-0.1.3.dist-info/pbr.json
oaserver-0.1.3.dist-info/regenerate.no
oaserver-0.1.3.dist-info/top_level.txt
oaserver_data/__init__.py
oaserver_data/relocate.py
