Metadata-Version: 2.0
Name: oaserver
Version: 0.1.3
Summary: Computation server oriented OpenAlea
Home-page: UNKNOWN
Author: revesansparole
Author-email: revesansparole@gmail.com
License: CeCILL-C
Platform: UNKNOWN
Classifier: Development Status :: 2 - Pre-Alpha
Classifier: Intended Audience :: Developers
Classifier: License :: OSI Approved :: BSD License
Classifier: Natural Language :: English
Classifier: Programming Language :: Python
Classifier: Programming Language :: Python :: 2
Classifier: Programming Language :: Python :: 2 :: Only
Classifier: Programming Language :: Python :: 2.7
Requires-Dist: requests
Requires-Dist: watchdog
Requires-Dist: web.py
